[
  {
    "id": 1,
    "first_name": "Missie",
    "last_name": "Hallatt",
    "username": "mhallatt0",
    "password": "hR0}dM\\<\"6Ggti!R",
    "email": "mhallatt0@cloudflare.com",
    "image": "http://dummyimage.com/106x100.png/5fa2dd/ffffff"
  },
  {
    "id": 2,
    "first_name": "Quentin",
    "last_name": "Hallewell",
    "username": "qhallewell1",
    "password": "rM8`n7Qb~#5",
    "email": "qhallewell1@shop-pro.jp",
    "image": "http://dummyimage.com/177x100.png/5fa2dd/ffffff"
  },
  {
    "id": 3,
    "first_name": "Gunar",
    "last_name": "Waiton",
    "username": "gwaiton2",
    "password": "gW6}CGrx6c7*",
    "email": "gwaiton2@discuz.net",
    "image": "http://dummyimage.com/103x100.png/cc0000/ffffff"
  },
  {
    "id": 4,
    "first_name": "Rebbecca",
    "last_name": "Scherer",
    "username": "rscherer3",
    "password": "wY8+R=rlW",
    "email": "rscherer3@google.fr",
    "image": "http://dummyimage.com/125x100.png/dddddd/000000"
  },
  {
    "id": 5,
    "first_name": "Rutter",
    "last_name": "Olander",
    "username": "rolander4",
    "password": "hO0$dq=GC@",
    "email": "rolander4@ifeng.com",
    "image": "http://dummyimage.com/185x100.png/dddddd/000000"
  },
  {
    "id": 6,
    "first_name": "Dela",
    "last_name": "Ebbage",
    "username": "debbage5",
    "password": "iG4~L%zKTx!9+",
    "email": "debbage5@washingtonpost.com",
    "image": "http://dummyimage.com/215x100.png/ff4444/ffffff"
  },
  {
    "id": 7,
    "first_name": "Xena",
    "last_name": "Congrave",
    "username": "xcongrave6",
    "password": "eT2%l,6@K?UH.&",
    "email": "xcongrave6@biglobe.ne.jp",
    "image": "http://dummyimage.com/103x100.png/dddddd/000000"
  },
  {
    "id": 8,
    "first_name": "Ethelbert",
    "last_name": "Baddow",
    "username": "ebaddow7",
    "password": "hE7`f1$QXZ,",
    "email": "ebaddow7@va.gov",
    "image": "http://dummyimage.com/234x100.png/cc0000/ffffff"
  },
  {
    "id": 9,
    "first_name": "Janek",
    "last_name": "Cradduck",
    "username": "jcradduck8",
    "password": "hR5>5K6l!",
    "email": "jcradduck8@elpais.com",
    "image": "http://dummyimage.com/121x100.png/5fa2dd/ffffff"
  },
  {
    "id": 10,
    "first_name": "Graehme",
    "last_name": "Pottes",
    "username": "gpottes9",
    "password": "qX0\"!y\\E&%8=o&Q",
    "email": "gpottes9@java.com",
    "image": "http://dummyimage.com/124x100.png/cc0000/ffffff"
  }
]
